{
  "project_info": {
    "project_number": "238268910343",
    "project_id": "crypto-text-57a89",
    "storage_bucket": "crypto-text-57a89.appspot.com"
  },
  "client": [
    {
      "client_info": {
        "mobilesdk_app_id": "1:238268910343:android:c1e11ffda194bd3c0f13a2",
        "android_client_info": {
          "package_name": "com.example.cryptotext"
        }
      },
      "oauth_client": [
        {
          "client_id": "238268910343-6euqf7vapefnlc4etm8mv9u86eb8ms3a.apps.googleusercontent.com",
          "client_type": 3
        }
      ],
      "api_key": [
        {
          "current_key": "AIzaSyCGHGq9bUEFie0Xag1d9h8ylidTP6yKLxQ"
        }
      ],
      "services": {
        "appinvite_service": {
          "other_platform_oauth_client": [
            {
              "client_id": "238268910343-6euqf7vapefnlc4etm8mv9u86eb8ms3a.apps.googleusercontent.com",
              "client_type": 3
            }
          ]
        }
      }
    }
  ],
  "configuration_version": "1"
}